ea_dash/EADrawerCollapsibleItem.py
ea_dash/EADrawerItem.py
ea_dash/EALayout.py
ea_dash/__init__.py
ea_dash/_imports_.py
ea_dash/ea_dash.min.js
ea_dash/ea_dash.min.js.map
ea_dash/metadata.json
ea_dash/package-info.json
ea_dash-0.0.15.dist-info/LICENSE
ea_dash-0.0.15.dist-info/METADATA
ea_dash-0.0.15.dist-info/WHEEL
ea_dash-0.0.15.dist-info/top_level.txt
ea_dash-0.0.15.dist-info/RECORD
