Metadata-Version: 2.1
Name: ea-dash
Version: 0.0.15
Summary: Dash versions of shared React components used in Energy Aspects applications
Author: Pavol Soltes <soltes.pavol@gmail.com>
License: MIT
Classifier: Framework :: Dash
License-File: LICENSE
